korbinian/MSA_normalisation.py
korbinian/__init__.py
korbinian/common.py
korbinian/fasta.py
korbinian/fastagap.py
korbinian/gap.py
korbinian/gap_figs.py
korbinian/psiblast.py
korbinian/run_korbinian.py
korbinian/simap_download.py
korbinian/simap_parse.py
korbinian/utils.py
korbinian/blast/__init__.py
korbinian/blast/blast_parser.py
korbinian/blast/blastp.py
korbinian/blast/psiblast.py
korbinian/cons_ratio/__init__.py
korbinian/cons_ratio/calc.py
korbinian/cons_ratio/compare_lists.py
korbinian/cons_ratio/cons_ratio.py
korbinian/cons_ratio/figs.py
korbinian/cons_ratio/gather.py
korbinian/cons_ratio/histogram.py
korbinian/cons_ratio/keywords.py
korbinian/cons_ratio/norm.py
korbinian/cons_ratio/slice.py
korbinian/cons_ratio/ssr.py
korbinian/filtering/__init__.py
korbinian/filtering/scampi.py
korbinian/filtering/signalP.py
korbinian/filtering/tmseg.py
korbinian/prot_list/SCAMPI.py
korbinian/prot_list/__init__.py
korbinian/prot_list/parse_OMPdb.py
korbinian/prot_list/parse_TMSEG.py
korbinian/prot_list/parse_boctopus.py
korbinian/prot_list/prot_list.py
korbinian/prot_list/uniprot_nonredundant.py
korbinian/prot_list/uniprot_parse.py
korbinian/prot_list/uniprot_retrieve.py
korbinian-0.3.4.dist-info/METADATA
korbinian-0.3.4.dist-info/RECORD
korbinian-0.3.4.dist-info/WHEEL
korbinian-0.3.4.dist-info/top_level.txt
