Metadata-Version: 2.1
Name: korbinian
Version: 0.3.4
Summary: Bioinformatic sequence analysis of membrane proteins.
Home-page: https://github.com/teese/korbinian
Author: Mark Teese
Author-email: mark.teese@checkmytumhomepage.de
License: MIT
Download-URL: https://github.com/teese/korbinian/archive/0.3.4.tar.gz
Project-URL: Wiki, https://github.com/teese/korbinian/wiki
Project-URL: LangoschLab, http://cbp.wzw.tum.de/index.php?id=9
Project-URL: TU_Muenchen, https://www.tum.de
Project-URL: Freising, https://en.wikipedia.org/wiki/Freising
Project-URL: KorbinianSaint, https://en.wikipedia.org/wiki/Corbinian
Project-URL: KorbinianBeer, https://www.weihenstephaner.de/unsere-biere/korbinian
Keywords: bioinformatics protein sequence membrane conservation evolution membranous soluble polypeptide BLAST SIMAP
Platform: UNKNOWN
Requires-Dist: numpy
Requires-Dist: matplotlib
Requires-Dist: pandas
Requires-Dist: seaborn
Requires-Dist: scipy
Requires-Dist: biopython
Requires-Dist: tqdm
